arabictest/__init__.py
arabictest/arabic_utils.py
arabictest/unit_root_tests.py
arabictest-1.0.0.dist-info/licenses/LICENSE
arabictest-1.0.0.dist-info/METADATA
arabictest-1.0.0.dist-info/WHEEL
arabictest-1.0.0.dist-info/top_level.txt
arabictest-1.0.0.dist-info/RECORD
