Metadata-Version: 2.4
Name: arabictest
Version: 1.0.0
Summary: Professional unit root testing package with Arabic language support for econometric research
Home-page: https://github.com/merwanroudane/arabictest
Author: Dr. Merwan Roudane
Author-email: "Dr. Merwan Roudane" <merwanroudane920@gmail.com>
Maintainer-email: "Dr. Merwan Roudane" <merwanroudane920@gmail.com>
License: MIT
Project-URL: Homepage, https://github.com/merwanroudane/arabictest
Project-URL: Documentation, https://github.com/merwanroudane/arabictest#readme
Project-URL: Repository, https://github.com/merwanroudane/arabictest
Project-URL: Issues, https://github.com/merwanroudane/arabictest/issues
Keywords: econometrics,unit root test,time series,ADF test,KPSS test,Phillips-Perron,stationarity,Arabic,statistics
Classifier: Development Status :: 5 - Production/Stable
Classifier: Intended Audience :: Science/Research
Classifier: Topic :: Scientific/Engineering :: Information Analysis
Classifier: License :: OSI Approved :: MIT License
Classifier: Programming Language :: Python :: 3
Classifier: Programming Language :: Python :: 3.8
Classifier: Programming Language :: Python :: 3.9
Classifier: Programming Language :: Python :: 3.10
Classifier: Programming Language :: Python :: 3.11
Classifier: Programming Language :: Python :: 3.12
Requires-Python: >=3.8
License-File: LICENSE
Requires-Dist: numpy>=1.20.0
Requires-Dist: pandas>=1.3.0
Requires-Dist: scipy>=1.7.0
Requires-Dist: statsmodels>=0.13.0
Requires-Dist: arch>=5.0.0
Requires-Dist: tabulate>=0.8.9
Requires-Dist: prettytable>=3.0.0
Requires-Dist: arabic-reshaper>=2.1.0
Requires-Dist: python-bidi>=0.4.2
Requires-Dist: colorama>=0.4.4
Provides-Extra: dev
Requires-Dist: pytest>=7.0.0; extra == "dev"
Requires-Dist: pytest-cov>=3.0.0; extra == "dev"
Requires-Dist: black>=22.0.0; extra == "dev"
Requires-Dist: flake8>=4.0.0; extra == "dev"
Dynamic: author
Dynamic: home-page
Dynamic: license-file
Dynamic: requires-python
